ansi2html/__init__.py
ansi2html/__main__.py
ansi2html/_version.py
ansi2html/converter.py
ansi2html/py.typed
ansi2html/style.py
ansi2html/util.py
ansi2html-1.9.1.dist-info/LICENSE
ansi2html-1.9.1.dist-info/METADATA
ansi2html-1.9.1.dist-info/WHEEL
ansi2html-1.9.1.dist-info/entry_points.txt
ansi2html-1.9.1.dist-info/top_level.txt
ansi2html-1.9.1.dist-info/RECORD
