Metadata-Version: 2.1
Name: ansi2html
Version: 1.9.1
Summary: Convert text with ANSI color codes to HTML or to LaTeX
Author-email: Ralph Bean <rbean@redhat.com>
Maintainer-email: Ralph Bean <rbean@redhat.com>
License: LGPLv3+
Project-URL: homepage, https://github.com/pycontribs/ansi2html
Project-URL: documentation, https://ansi2html.readthedocs.io/
Project-URL: repository, https://github.com/pycontribs/ansi2html
Project-URL: changelog, https://github.com/pycontribs/ansi2html/releases
Keywords: ansi,html,color
Classifier: Development Status :: 5 - Production/Stable
Classifier: Environment :: Console
Classifier: Intended Audience :: Developers
Classifier: Intended Audience :: System Administrators
Classifier: License :: OSI Approved :: MIT License
Classifier: Operating System :: MacOS
Classifier: Operating System :: POSIX
Classifier: License :: OSI Approved :: GNU Lesser General Public License v3 or later (LGPLv3+)
Classifier: Programming Language :: Python :: 3
Classifier: Programming Language :: Python :: 3.7
Classifier: Programming Language :: Python :: 3.8
Classifier: Programming Language :: Python :: 3.9
Classifier: Programming Language :: Python :: 3.10
Classifier: Programming Language :: Python :: 3.11
Classifier: Programming Language :: Python :: 3.12
Classifier: Programming Language :: Python :: 3 :: Only
Classifier: Programming Language :: Python
Classifier: Topic :: Software Development :: Quality Assurance
Classifier: Topic :: Software Development :: Testing
Classifier: Topic :: System :: Systems Administration
Classifier: Topic :: Text Processing :: Markup :: HTML
Classifier: Topic :: Text Processing :: Markup
Classifier: Topic :: Text Processing
Classifier: Topic :: Utilities
Requires-Python: >=3.7
License-File: LICENSE
Requires-Dist: importlib-metadata; python_version < "3.8"
Requires-Dist: typing_extensions; python_version < "3.8"
Provides-Extra: docs
Requires-Dist: mkdocs; extra == "docs"
Requires-Dist: mkdocs-material; extra == "docs"
Requires-Dist: mkdocs-material-extensions; extra == "docs"
Requires-Dist: mkdocstrings; extra == "docs"
Requires-Dist: mkdocstrings-python; extra == "docs"
Requires-Dist: pymdown-extensions; extra == "docs"
Provides-Extra: test
Requires-Dist: pytest; extra == "test"
Requires-Dist: pytest-cov; extra == "test"
